characterization_ams/__init__.py
characterization_ams/_version.py
characterization_ams/emva/__init__.py
characterization_ams/emva/emva.py
characterization_ams/emva/routines.py
characterization_ams/standard_tests/__init__.py
characterization_ams/standard_tests/ptc.py
characterization_ams/stats_engine/__init__.py
characterization_ams/stats_engine/pixelwise_stats.py
characterization_ams/stats_engine/stats.py
characterization_ams/unittests/__init__.py
characterization_ams/unittests/image_generator.py
characterization_ams/unittests/test_emva.py
characterization_ams/unittests/test_ptc.py
characterization_ams/unittests/test_stats.py
characterization_ams/unittests/datasets/__init__.py
characterization_ams/unittests/datasets/test_emva.csv
characterization_ams/utilities/__init__.py
characterization_ams/utilities/calc.py
characterization_ams/utilities/default-renames.yaml
characterization_ams/utilities/htmls_.py
characterization_ams/utilities/image.py
characterization_ams/utilities/utilities.py
characterization_ams-1.1.4.dist-info/LICENSE
characterization_ams-1.1.4.dist-info/METADATA
characterization_ams-1.1.4.dist-info/WHEEL
characterization_ams-1.1.4.dist-info/top_level.txt
characterization_ams-1.1.4.dist-info/RECORD
