Metadata-Version: 2.1
Name: characterization-ams
Version: 1.1.4
Summary: package for ams char
Author: ams
Author-email: denver.lloyd@ams-osram.com
License: MIT License
Classifier: Programming Language :: Python :: 3
Classifier: License :: OSI Approved :: MIT License
Classifier: Operating System :: OS Independent
Requires-Python: >=3.6
License-File: LICENSE
Requires-Dist: pandas
Requires-Dist: scipy
Requires-Dist: collections-extended
Requires-Dist: lxml
Requires-Dist: PyYAML
Requires-Dist: sympy
Requires-Dist: numpy (>=1.4.1) ; platform_system == "Windows"
Requires-Dist: pillow ; platform_system == "Windows"
Requires-Dist: matplotlib ; platform_system == "Windows"
